MANIFEST.in
ez_setup.py
setup.py
followit/LICENSE
followit/TODO.rst
followit/__init__.py
followit/models.py
followit/urls.py
followit/utils.py
followit/views.py
followit.egg-info/PKG-INFO
followit.egg-info/SOURCES.txt
followit.egg-info/dependency_links.txt
followit.egg-info/top_level.txt
followit/tests/README.rst
followit/tests/__init__.py
followit/tests/models.py
followit/tests/runtests.py
followit/tests/settings.py
followit/tests/tests.py